{
  "beers": [
    {
      "id": 1,
      "name": "Oh So Flattening",
      "description": "Isebania",
      "image_url": "https://i.ibb.co/wQ4G0w1/flatiron-brew.png",
      "reviews": [
        "It's flat! Just the way I like it!!",
        "Is this the real beer, is this just fantasy?",
        "I've always hated bubbles going up my nose, so this is absolutely delightful.",
        "Flat straight out of the bottle! No more waiting for the fizziness to subside. Thank you FlattaBeer!! I love you!!!"
      ]
    }
    
  ]
}